modbus_server/__init__.py
modbus_server/modbus_datastore.py
modbus_server/modbus_server.py
modbus_server-0.2.3.dist-info/LICENSE
modbus_server-0.2.3.dist-info/WHEEL
modbus_server-0.2.3.dist-info/METADATA
modbus_server-0.2.3.dist-info/RECORD
