Metadata-Version: 2.1
Name: modbus_server
Version: 0.2.3
Summary: Easy-to-use ModbusTCP Server in pure Python 
Author: Christoph Kattmann
Author-email: christoph.kattmann@bss-hs.de
Classifier: License :: OSI Approved :: MIT License
